jupyterlab_thredds/__init__.py
jupyterlab_thredds/config.py
jupyterlab_thredds/crawler.py
jupyterlab_thredds/version.py
jupyterlab_thredds/fetchers/__init__.py
jupyterlab_thredds/fetchers/esgf.py
jupyterlab_thredds/fetchers/thredds.py
jupyterlab_thredds-0.5.0.data/data/etc/jupyter/jupyter_notebook_config.d/jupyterlab_thredds.json
jupyterlab_thredds-0.5.0.dist-info/LICENSE
jupyterlab_thredds-0.5.0.dist-info/METADATA
jupyterlab_thredds-0.5.0.dist-info/WHEEL
jupyterlab_thredds-0.5.0.dist-info/top_level.txt
jupyterlab_thredds-0.5.0.dist-info/RECORD
