Metadata-Version: 2.1
Name: jupyterlab-thredds
Version: 0.5.0
Summary: A Jupyter Notebook server extension which crawls a thredds catalog
Home-page: https://github.com/eWaterCycle/jupyterlab_thredds
Author: S. Verhoeven
Author-email: s.verhoeven@esciencecenter.nl
License: Apache-2.0
Keywords: Jupyter,JupyterLab,Thredds
Platform: Linux
Platform: Mac OS X
Platform: Windows
Classifier: Intended Audience :: Developers
Classifier: Intended Audience :: System Administrators
Classifier: Intended Audience :: Science/Research
Classifier: Programming Language :: Python
Classifier: Programming Language :: Python :: 3
Classifier: Programming Language :: Python :: 3.6
Classifier: Programming Language :: Python :: 3.7
Classifier: Programming Language :: Python :: 3.8
Classifier: License :: OSI Approved :: Apache Software License
Requires-Python: >=3.6
Requires-Dist: notebook
Requires-Dist: siphon
Requires-Dist: xarray
Requires-Dist: netCDF4
Requires-Dist: ipyleaflet
Requires-Dist: OWSLib
Requires-Dist: traitlets
Requires-Dist: aiohttp
